agent_server/__init__.py
agent_server/alembic/env.py
agent_server/alembic/script.py.mako
agent_server/alembic/versions/20250817172544_initial_schema.py
agent_server/alembic/versions/20250830161758_add_context.py
agent_server/alembic/versions/20250831174511_add_cascade_delete_for_runs_thread_fkey.py
agent_server/alembic/versions/20250913193817_add_version_table.py
agent_server/alembic/versions/20250913213535_add_metadata_for_assistant_table_and_.py
agent_server/alembic/versions/20251115152415_migrate_run_status_to_langgraph_.py
agent_server/alembic.ini
agent_server/api/__init__.py
agent_server/api/assistants.py
agent_server/api/runs.py
agent_server/api/store.py
agent_server/api/threads.py
agent_server/auth.py
agent_server/cli.py
agent_server/config.py
agent_server/constants.py
agent_server/core/__init__.py
agent_server/core/app_loader.py
agent_server/core/auth_ctx.py
agent_server/core/auth_deps.py
agent_server/core/auth_middleware.py
agent_server/core/database.py
agent_server/core/health.py
agent_server/core/orm.py
agent_server/core/route_merger.py
agent_server/core/serializers/__init__.py
agent_server/core/serializers/base.py
agent_server/core/serializers/general.py
agent_server/core/serializers/langgraph.py
agent_server/core/sse.py
agent_server/main.py
agent_server/middleware/__init__.py
agent_server/middleware/double_encoded_json.py
agent_server/middleware/logger_middleware.py
agent_server/models/__init__.py
agent_server/models/assistants.py
agent_server/models/auth.py
agent_server/models/enums.py
agent_server/models/errors.py
agent_server/models/runs.py
agent_server/models/store.py
agent_server/models/threads.py
agent_server/observability/__init__.py
agent_server/observability/base.py
agent_server/observability/langfuse_integration.py
agent_server/services/__init__.py
agent_server/services/assistant_service.py
agent_server/services/base_broker.py
agent_server/services/broker.py
agent_server/services/event_converter.py
agent_server/services/event_store.py
arcsitegraph-0.1.16.dist-info/WHEEL
arcsitegraph-0.1.16.dist-info/entry_points.txt
arcsitegraph-0.1.16.dist-info/METADATA
arcsitegraph-0.1.16.dist-info/RECORD
