Metadata-Version: 2.3
Name: arcsitegraph
Version: 0.1.16
Summary: Open source LangGraph Platform alternative - Self-hosted AI agent backend with FastAPI and PostgreSQL. Zero vendor lock-in, full control over your agent infrastructure.
Keywords: langgraph,ai-agents,self-hosted,agent-backend,fastapi,postgresql,langchain,agent-protocol
Author: Muhammad Ibrahim
Author-email: Muhammad Ibrahim <mibrahim37612@gmail.com>
Classifier: Development Status :: 3 - Alpha
Classifier: Intended Audience :: Developers
Classifier: License :: OSI Approved :: Apache Software License
Classifier: Programming Language :: Python :: 3
Classifier: Programming Language :: Python :: 3.11
Classifier: Programming Language :: Python :: 3.12
Classifier: Topic :: Software Development :: Libraries :: Python Modules
Classifier: Topic :: Scientific/Engineering :: Artificial Intelligence
Requires-Dist: alembic>=1.16.4
Requires-Dist: asyncpg>=0.30.0
Requires-Dist: fastapi>=0.116.1
Requires-Dist: greenlet>=3.2.3
Requires-Dist: langchain-openai>=1.0.3
Requires-Dist: langgraph>=1.0.3
Requires-Dist: langchain>=1.0.8
Requires-Dist: langgraph-checkpoint-postgres>=2.0.23
Requires-Dist: psycopg[binary]>=3.2.9
Requires-Dist: pydantic>=2.11.7
Requires-Dist: pyjwt>=2.10.1
Requires-Dist: python-dotenv>=1.1.1
Requires-Dist: sqlalchemy>=2.0.0
Requires-Dist: uvicorn>=0.35.0
Requires-Dist: langfuse>=3.3.4
Requires-Dist: structlog>=25.4.0
Requires-Dist: asgi-correlation-id>=4.3.4
Maintainer: Muhammad Ibrahim
Maintainer-email: Muhammad Ibrahim <mibrahim37612@gmail.com>
Requires-Python: >=3.11
Project-URL: Bug Tracker, https://github.com/ibbybuilds/aegra/issues
Project-URL: Documentation, https://github.com/ibbybuilds/aegra#readme
Project-URL: Feature Requests, https://github.com/ibbybuilds/aegra/issues
Project-URL: Homepage, https://github.com/ibbybuilds/aegra
Project-URL: Repository, https://github.com/ibbybuilds/aegra
